POAP-0.1.26.dist-info/.DS_Store
POAP-0.1.26.dist-info/DESCRIPTION.rst
POAP-0.1.26.dist-info/METADATA
POAP-0.1.26.dist-info/RECORD
POAP-0.1.26.dist-info/WHEEL
POAP-0.1.26.dist-info/metadata.json
POAP-0.1.26.dist-info/top_level.txt
poap/__init__.py
poap/controller.py
poap/mpiserve.py
poap/strategy.py
poap/tcpserve.py
poap/test/__init__.py
poap/test/monitor.py
poap/test/mpi_silly.py
poap/test/test_coroutine_strategy.py
poap/test/test_fixed_strategy.py
poap/test/test_input_strategy.py
poap/test/test_maxterm_strategy.py
poap/test/test_mpi_process_worker.py
poap/test/test_mpiserve.py
poap/test/test_process_worker.py
poap/test/test_simteam_controller.py
poap/test/test_strategies.py
poap/test/test_tcpserve.py
poap/test/test_thread_controller.py
poap/test/test_thread_strategy.py
