Metadata-Version: 2.0
Name: POAP
Version: 0.1.26
Summary: Python Optimization Asynchronous Plumbing.
Home-page: http://pypi.python.org/pypi/POAP/
Author: David Bindel
Author-email: bindel@cornell.edu
License: LICENSE.txt
Platform: UNKNOWN
Classifier: Development Status :: 3 - Alpha
Classifier: Intended Audience :: Developers
Classifier: License :: OSI Approved :: MIT License
Classifier: Programming Language :: Python :: 2.7
Classifier: Programming Language :: Python :: 3
Classifier: Programming Language :: Python :: 3.2
Classifier: Programming Language :: Python :: 3.3
Classifier: Programming Language :: Python :: 3.4
